recodex/__init__.py
recodex/aliases.yaml
recodex/client.py
recodex/client_factory.py
recodex/client_components/alias_container.py
recodex/client_components/client_response.py
recodex/client_components/endpoint_resolver.py
recodex/client_components/swagger_validator.py
recodex/generated/setup.py
recodex/generated/swagger.yaml
recodex/generated/swagger_client/__init__.py
recodex/generated/swagger_client/api_client.py
recodex/generated/swagger_client/configuration.py
recodex/generated/swagger_client/rest.py
recodex/generated/swagger_client/api/__init__.py
recodex/generated/swagger_client/api/default_api.py
recodex/generated/swagger_client/models/__init__.py
recodex/generated/swagger_client/models/assignmentsolutions_id_body.py
recodex/generated/swagger_client/models/brokerreports_error_body.py
recodex/generated/swagger_client/models/comment_id_private_body.py
recodex/generated/swagger_client/models/comments_id_body.py
recodex/generated/swagger_client/models/config_variables_body.py
recodex/generated/swagger_client/models/course_id_bind_body.py
recodex/generated/swagger_client/models/course_id_create_body.py
recodex/generated/swagger_client/models/emails_regularusers_body.py
recodex/generated/swagger_client/models/emails_supervisors_body.py
recodex/generated/swagger_client/models/exercise_id_presubmit_body.py
recodex/generated/swagger_client/models/exercise_id_resubmitall_body.py
recodex/generated/swagger_client/models/exercise_id_submit_body.py
recodex/generated/swagger_client/models/exerciseassignments_id_body.py
recodex/generated/swagger_client/models/exercises_id_body.py
recodex/generated/swagger_client/models/exercises_list_body.py
recodex/generated/swagger_client/models/externallogin_service_body.py
recodex/generated/swagger_client/models/filters.py
recodex/generated/swagger_client/models/forgottenpassword_change_body.py
recodex/generated/swagger_client/models/forgottenpassword_validatepasswordstrength_body.py
recodex_pylib-0.2.2.dist-info/licenses/LICENSE
recodex_pylib-0.2.2.dist-info/METADATA
recodex_pylib-0.2.2.dist-info/WHEEL
recodex_pylib-0.2.2.dist-info/top_level.txt
recodex_pylib-0.2.2.dist-info/RECORD
