Metadata-Version: 2.4
Name: recodex-pylib
Version: 0.2.2
Summary: A python library for ReCodEx API calls.
Author-email: Vojtech Kloda <vojtech.kloda@gmail.com>, Martin Kruliš <krulis@d3s.mff.cuni.cz>
Project-URL: Homepage, https://github.com/ReCodEx/pylib
Project-URL: Issues, https://github.com/ReCodEx/pylib/issues
Classifier: Programming Language :: Python :: 3
Classifier: Operating System :: OS Independent
Classifier: License :: OSI Approved :: MIT License
Requires-Python: >=3.11
License-File: LICENSE
Requires-Dist: setuptools>=61.0
Requires-Dist: certifi>=14.05.14
Requires-Dist: six>=1.10
Requires-Dist: python_dateutil>=2.5.3
Requires-Dist: urllib3>=1.15.1
Requires-Dist: prance>=23.6.21.0
Requires-Dist: openapi-spec-validator>=0.7.1
Requires-Dist: jsonschema>=4.23.0
Requires-Dist: pyyaml>=5.2b1
Requires-Dist: appdirs>=1.4.4
Requires-Dist: pyjwt>=2.10.1
Dynamic: license-file
